clipyarser/__init__.py
clipyarser/clipyarser.py
clipyarser-0.2.0.dist-info/LICENSE
clipyarser-0.2.0.dist-info/WHEEL
clipyarser-0.2.0.dist-info/METADATA
clipyarser-0.2.0.dist-info/RECORD
