Metadata-Version: 2.1
Name: clipyarser
Version: 0.2.0
Summary: A simple, declarative and easy-testable command line argument parser
Home-page: https://github.com/linuskmr/clipyarser
License: MIT
Keywords: cli,parser,argparse,argumentparser
Author: Linus
Author-email: linuskmr.dev@gmail.com
Requires-Python: >=3.8,<4.0
Classifier: License :: OSI Approved :: MIT License
Classifier: Programming Language :: Python :: 3
Classifier: Programming Language :: Python :: 3.10
Classifier: Programming Language :: Python :: 3.8
Classifier: Programming Language :: Python :: 3.9
Project-URL: Repository, https://github.com/linuskmr/clipyarser
